d2lmf/__init__.py
d2lmf/__main__.py
d2lmf/d2lmf.py
d2lmf-1.0.0.dist-info/DESCRIPTION.rst
d2lmf-1.0.0.dist-info/METADATA
d2lmf-1.0.0.dist-info/RECORD
d2lmf-1.0.0.dist-info/WHEEL
d2lmf-1.0.0.dist-info/entry_points.txt
d2lmf-1.0.0.dist-info/metadata.json
d2lmf-1.0.0.dist-info/top_level.txt
